iterflat/__init__.py
iterflat/core/__init__.py
iterflat/tests/__init__.py
iterflat/tests/test_0.py
iterflat-0.1.5.dist-info/licenses/LICENSE.txt
iterflat-0.1.5.dist-info/METADATA
iterflat-0.1.5.dist-info/WHEEL
iterflat-0.1.5.dist-info/top_level.txt
iterflat-0.1.5.dist-info/RECORD
